snakewhisper/__init__.py
snakewhisper/__main__.py
snakewhisper-1.1.1.dist-info/LICENSE
snakewhisper-1.1.1.dist-info/METADATA
snakewhisper-1.1.1.dist-info/WHEEL
snakewhisper-1.1.1.dist-info/top_level.txt
snakewhisper-1.1.1.dist-info/RECORD
