Metadata-Version: 2.1
Name: snakewhisper
Version: 1.1.1
Summary: Proof of concept of an end-to-end encrypted peer-to-peer chat program written in Python.
Home-page: https://github.com/slightlyskepticalpotat/snakewhisper
Author: Anthony Chen
License: UNKNOWN
Platform: UNKNOWN
Classifier: Programming Language :: Python :: 3
Classifier: License :: OSI Approved :: GNU Affero General Public License v3
Classifier: Operating System :: OS Independent
Requires-Python: >=3.6
License-File: LICENSE
Requires-Dist: cryptography (>=3.4.7)
